{
    "properties": {
        "_id": {
            "bsonType": "objectId"
        },
        "authors": {
            "bsonType": "array",
            "items": {
                "bsonType": "string"
            }
        },
        "cloudinary_id": {
            "bsonType": "string"
        },
        "date_downloaded": {
            "bsonType": "string"
        },
        "date_modified": {
            "bsonType": "string"
        },
        "date_published": {
            "bsonType": "string"
        },
        "date_submitted": {
            "bsonType": "string"
        },
        "description": {
            "bsonType": "string"
        },
        "editor_notes": {
            "bsonType": "string"
        },
        "epoch_date_downloaded": {
            "bsonType": "int"
        },
        "epoch_date_modified": {
            "bsonType": "int"
        },
        "epoch_date_published": {
            "bsonType": "int"
        },
        "epoch_date_submitted": {
            "bsonType": "int"
        },
        "epoch_incident_date": {
            "bsonType": "int"
        },
        "flag": {
            "bsonType": "bool"
        },
        "image_url": {
            "bsonType": "string"
        },
        "incident_date": {
            "bsonType": "string"
        },
        "language": {
            "bsonType": "string"
        },
        "plain_text": {
            "bsonType": "string"
        },
        "ref_number": {
            "bsonType": "int"
        },
        "report_number": {
            "bsonType": "int"
        },
        "source_domain": {
            "bsonType": "string"
        },
        "submitters": {
            "bsonType": "array",
            "items": {
                "bsonType": "string"
            }
        },
        "tags": {
            "bsonType": "array",
            "items": {
                "bsonType": "string"
            }
        },
        "text": {
            "bsonType": "string"
        },
        "title": {
            "bsonType": "string"
        },
        "url": {
            "bsonType": "string"
        }
    },
    "required": [
        "report_number",
        "ref_number",
        "date_downloaded",
        "date_modified",
        "date_published",
        "date_submitted",
        "epoch_date_downloaded",
        "epoch_date_modified",
        "epoch_date_published",
        "epoch_date_submitted",
        "image_url",
        "cloudinary_id",
        "authors",
        "submitters",
        "title",
        "text",
        "url",
        "source_domain"
    ],
    "title": "report"
}
